replite/__init__.py
replite/_version.py
replite/labextension/build_log.json
replite/labextension/package.json
replite/labextension/static/lib_index_js.fdea13716e691d9b14ea.js
replite/labextension/static/lib_index_js.fdea13716e691d9b14ea.js.map
replite/labextension/static/remoteEntry.e2ef00a0afbb7a845f12.js
replite/labextension/static/remoteEntry.e2ef00a0afbb7a845f12.js.map
replite/labextension/static/style.js
replite/labextension/static/style_index_js.42b6da3f5f542f9887d7.js
replite/labextension/static/style_index_js.42b6da3f5f542f9887d7.js.map
replite/labextension/static/vendors-node_modules_css-loader_dist_runtime_api_js-node_modules_css-loader_dist_runtime_cssW-72eba1.1653ca3a3a8669abf57d.js
replite/labextension/static/vendors-node_modules_css-loader_dist_runtime_api_js-node_modules_css-loader_dist_runtime_cssW-72eba1.1653ca3a3a8669abf57d.js.map
replite/labextension/static/vendors-node_modules_jupyterlite_ui-components_lib_index_js.7d38df19a248d7530b83.js
replite/labextension/static/vendors-node_modules_jupyterlite_ui-components_lib_index_js.7d38df19a248d7530b83.js.map
replite-0.1.1.data/data/share/jupyter/labextensions/replite/build_log.json
replite-0.1.1.data/data/share/jupyter/labextensions/replite/install.json
replite-0.1.1.data/data/share/jupyter/labextensions/replite/package.json
replite-0.1.1.data/data/share/jupyter/labextensions/replite/static/lib_index_js.fdea13716e691d9b14ea.js
replite-0.1.1.data/data/share/jupyter/labextensions/replite/static/lib_index_js.fdea13716e691d9b14ea.js.map
replite-0.1.1.data/data/share/jupyter/labextensions/replite/static/remoteEntry.e2ef00a0afbb7a845f12.js
replite-0.1.1.data/data/share/jupyter/labextensions/replite/static/remoteEntry.e2ef00a0afbb7a845f12.js.map
replite-0.1.1.data/data/share/jupyter/labextensions/replite/static/style.js
replite-0.1.1.data/data/share/jupyter/labextensions/replite/static/style_index_js.42b6da3f5f542f9887d7.js
replite-0.1.1.dist-info/LICENSE
replite-0.1.1.dist-info/METADATA
replite-0.1.1.dist-info/WHEEL
replite-0.1.1.dist-info/top_level.txt
replite-0.1.1.dist-info/RECORD
